npiai/__init__.py
npiai/agent/__init__.py
npiai/cloud/__init__.py
npiai/cloud/_client.py
npiai/cloud/_connect.py
npiai/cloud/_context.py
npiai/cloud/_runtime.py
npiai/constant/app.py
npiai/container/container.py
npiai/context/__init__.py
npiai/context/context.py
npiai/context/manager.py
npiai/core/__init__.py
npiai/core/base.py
npiai/core/browser/__init__.py
npiai/core/browser/_navigator.py
npiai/core/browser/_playwright.py
npiai/core/callback/__init__.py
npiai/core/callback/_callback.py
npiai/core/hitl.py
npiai/core/tool/__init__.py
npiai/core/tool/_agent.py
npiai/core/tool/_browser.py
npiai/core/tool/_function.py
npiai/error/__init__.py
npiai/error/auth.py
npiai/hitl_handler/__init__.py
npiai/hitl_handler/console.py
npiai/integration/langchain/__init__.py
npiai/integration/langchain/create_tool.py
npiai/integration/langchain/toolkit.py
npiai/llm/__init__.py
npiai/llm/llm.py
npiai/runtime/__init__.py
npiai/tools/__init__.py
npiai/tools/discord/__test__/__init__.py
npiai/tools/discord/__test__/send_and_wait.py
npiai/tools/discord/app.py
npiai/tools/github/__test__/__init__.py
npiai/tools/github/__test__/close_issue.spec.py
npiai/tools/github/__test__/close_pull_request.spec.py
npiai/tools/github/__test__/create_issue.spec.py
npiai/tools/github/__test__/create_pull_request.spec.py
npiai/tools/github/__test__/star_and_fork.py
npiai/tools/github/__test__/update_issue.spec.py
npiai/tools/github/__test__/watch_issues.py
npiai/tools/github/app.py
npiai/tools/github/npi.yml
npiai/tools/google/calendar/__test__/__init__.py
npiai/tools/google/calendar/__test__/retrive.spec.py
npiai/tools/google/calendar/app.py
npiai/tools/google/gmail/__test__/__init__.py
npiai/tools/google/gmail/__test__/add_labels.spec.py
npiai/tools/google/gmail/__test__/wait_for_reply.spec.py
npiai/tools/google/gmail/app.py
npiai/tools/google/gmail/client.py
npiai/tools/slack/__test__/__init__.py
npiai/tools/slack/__test__/send_and_wait.py
npiai/tools/slack/app.py
npiai/tools/twilio/app.py
npiai-0.2.3.dist-info/LICENSE
npiai-0.2.3.dist-info/METADATA
npiai-0.2.3.dist-info/WHEEL
npiai-0.2.3.dist-info/RECORD
