Metadata-Version: 2.1
Name: npiai
Version: 0.2.3
Summary: 
Author: wenfeng
Author-email: w@npi.ai
Requires-Python: >=3.10,<4.0
Classifier: Programming Language :: Python :: 3
Classifier: Programming Language :: Python :: 3.10
Classifier: Programming Language :: Python :: 3.11
Classifier: Programming Language :: Python :: 3.12
Requires-Dist: boto3 (>=1.34.127,<2.0.0)
Requires-Dist: discord (>=2.3.2,<3.0.0)
Requires-Dist: discord-py (>=2.3.2,<3.0.0)
Requires-Dist: docstring-parser (>=0.16,<0.17)
Requires-Dist: fastapi (>=0.111.0,<0.112.0)
Requires-Dist: google-api-python-client (>=2.132.0,<3.0.0)
Requires-Dist: google-auth-httplib2 (>=0.2.0,<0.3.0)
Requires-Dist: google-auth-oauthlib (>=1.2.0,<2.0.0)
Requires-Dist: grpcio (>=1.62.1,<2.0.0)
Requires-Dist: httplib2 (>=0.22.0,<0.23.0)
Requires-Dist: langchain (>=0.2.7,<0.3.0)
Requires-Dist: litellm (==1.41.0)
Requires-Dist: loguru (>=0.7.2,<0.8.0)
Requires-Dist: markdown (>=3.6,<4.0)
Requires-Dist: markdownify (>=0.12.1,<0.13.0)
Requires-Dist: openai (>=1.30.3,<2.0.0)
Requires-Dist: playwright (>=1.44.0,<2.0.0)
Requires-Dist: protobuf (>=5.27.2,<6.0.0)
Requires-Dist: pydantic (>=2.7.3,<3.0.0)
Requires-Dist: pygithub (>=2.3.0,<3.0.0)
Requires-Dist: python-slugify (>=8.0.4,<9.0.0)
Requires-Dist: pyyaml (>=6.0.1,<7.0.0)
Requires-Dist: questionary (>=2.0.1,<3.0.0)
Requires-Dist: simplegmail (>=4.1.1,<5.0.0)
Requires-Dist: slack-sdk (>=3.27.2,<4.0.0)
Requires-Dist: termcolor (>=2.4.0,<3.0.0)
Requires-Dist: twilio (>=9.1.0,<10.0.0)
